halca1006/__init__.py
halca1006/hal.py
halca1006-0.0.2.dist-info/LICENSE.txt
halca1006-0.0.2.dist-info/METADATA
halca1006-0.0.2.dist-info/WHEEL
halca1006-0.0.2.dist-info/top_level.txt
halca1006-0.0.2.dist-info/RECORD
