Metadata-Version: 2.1
Name: halca1006
Version: 0.0.2
Summary: Protocol support for the HAL CA1006 multi-zone amplifier
Home-page: https://github.com/bradkeifer/halca1006
Author: Brad Keifer
Author-email: bradkeifer@icloud.com
License: UNKNOWN
Project-URL: Bug Tracker, https://github.com/bradkeifer/halca1006/issues
Platform: UNKNOWN
Classifier: Development Status :: 3 - Alpha
Classifier: License :: OSI Approved :: GNU General Public License v3 or later (GPLv3+)
Classifier: Operating System :: OS Independent
Classifier: Programming Language :: Python :: 3
Requires-Python: >=3.7
